qbm/__init__.py
qbm/models/BQRBM.py
qbm/models/QBMBase.py
qbm/models/__init__.py
qbm/simulation/__init__.py
qbm/simulation/simulation.py
qbm/utils/__init__.py
qbm/utils/discretization.py
qbm/utils/misc.py
qbm/utils/transformations.py
qbm-0.1.2.dist-info/METADATA
qbm-0.1.2.dist-info/WHEEL
qbm-0.1.2.dist-info/licenses/LICENSE
qbm-0.1.2.dist-info/RECORD
