Metadata-Version: 2.1
Name: qbm
Version: 0.1.2
Summary: A Python package for training and analyzing quantum Boltzmann machines
Project-URL: Homepage, https://github.com/cameronperot/qbm
Project-URL: Documentation, https://cameronperot.github.io/qbm/html/index.html
Author: Cameron Perot
License-File: LICENSE
Classifier: Development Status :: 4 - Beta
Classifier: Intended Audience :: Science/Research
Classifier: License :: OSI Approved :: MIT License
Classifier: Operating System :: OS Independent
Classifier: Programming Language :: Python :: 3.9
Classifier: Programming Language :: Python :: 3.10
Classifier: Programming Language :: Python :: 3.11
Classifier: Topic :: Scientific/Engineering
Requires-Python: >=3.9
Requires-Dist: dwave-ocean-sdk>=4.2.0
Requires-Dist: matplotlib>=3.4.3
Requires-Dist: numpy>=1.20.3
Requires-Dist: pandas>=1.3.3
Requires-Dist: scipy>=1.7.1
Provides-Extra: dev
Requires-Dist: black; extra == 'dev'
Requires-Dist: flake8; extra == 'dev'
Requires-Dist: isort; extra == 'dev'
Requires-Dist: m2r2; extra == 'dev'
Requires-Dist: pytest; extra == 'dev'
Requires-Dist: pytest-cov; extra == 'dev'
Requires-Dist: python-language-server; extra == 'dev'
Requires-Dist: sphinx; extra == 'dev'
Requires-Dist: sphinx-rtd-theme; extra == 'dev'
Requires-Dist: twine; extra == 'dev'
Provides-Extra: ipython
Requires-Dist: ipykernel; extra == 'ipython'
Requires-Dist: ipython; extra == 'ipython'
